setup.py
basis/__init__.py
basis/basis.py
basis/testbasis.py
basis/setup/__init__.py
basis/setup/arguments.py
basis/setup/context.py
basis/setup/pbzx.py
basis/setup/registry.py
basis/setup/version.py
basis/setup/helpers/__init__.py
basis/setup/helpers/shell.py
basis/setup/logging/__init__.py
basis/setup/logging/constants.py
basis/setup/logging/log_entry.py
basis/setup/logging/logger.py
basis/setup/logging/rendering.py
basis/setup/logging/renderers/__init__.py
basis/setup/logging/renderers/file_poster.py
basis/setup/logging/renderers/http_poster.py
basis/setup/logging/renderers/notification_poster.py
basis/setup/logging/renderers/terminal_poster.py
basis/setup/logging/renderers/internal/__init__.py
basis/setup/logging/renderers/internal/notify.py
basis/setup/step/__init__.py
basis/setup/step/exceptions.py
basis/setup/step/packagemanager.py
basis/setup/step/shellmanager.py
basis/setup/step/stepbase.py
basis/setup/step/stepresult.py
basis/setup/step/scoped_step/__init__.py
basis/setup/step/scoped_step/scoped_step.py
basis/test/__init__.py
basis/test/integration.py
basis/test/sampleteststeps.py
basis/test/unit/__init__.py
basis/test/unit/all.py
basis/test/unit/arguments.py
basis/test/unit/context.py
basis/test/unit/log.py
basis/test/unit/registry.py
basis/test/unit/version.py
basis/test/unit/step/__init__.py
basis/test/unit/step/packagemanager.py
basis/test/unit/step/shellmanager.py
basis/test/unit/step/stepbase.py
basis/test/unit/step/scoped_step/__init__.py
basis/test/unit/step/scoped_step/scoped_step.py
jtitor_basis.egg-info/PKG-INFO
jtitor_basis.egg-info/SOURCES.txt
jtitor_basis.egg-info/dependency_links.txt
jtitor_basis.egg-info/entry_points.txt
jtitor_basis.egg-info/requires.txt
jtitor_basis.egg-info/top_level.txt