Metadata-Version: 1.0
Name: jtitor-basis
Version: 0.1.19
Summary: Framework for cross-platform scripts that run in stages. Privately listed since it's not quite done.
Home-page: http://pypi.python.org/pypi/jtitor_basis/0.1.19/
Author: jTitor
Author-email: name@addr.ess
License: MIT
Platform: UNKNOWN
